setup.py
pyramid_subscribers_beaker_https_session/__init__.py
pyramid_subscribers_beaker_https_session.egg-info/PKG-INFO
pyramid_subscribers_beaker_https_session.egg-info/SOURCES.txt
pyramid_subscribers_beaker_https_session.egg-info/dependency_links.txt
pyramid_subscribers_beaker_https_session.egg-info/not-zip-safe
pyramid_subscribers_beaker_https_session.egg-info/requires.txt
pyramid_subscribers_beaker_https_session.egg-info/top_level.txt