Metadata-Version: 1.1
Name: pyramid-subscribers-beaker-https-session
Version: 0.1.0
Summary: provides for a 'session_https' secure session object
Home-page: https://github.com/jvanasco/pyramid_subscribers_beaker_https_session
Author: Jonathan Vanasco
Author-email: jonathan@findmeon.com
License: BSD-derived (http://www.repoze.org/LICENSE.txt)
Keywords: web pyramid beaker
Platform: UNKNOWN
Classifier: Intended Audience :: Developers
Classifier: Framework :: Pyramid
Classifier: Programming Language :: Python
Classifier: License :: Repoze Public License
